Metadata-Version: 2.4
Name: whatsnext
Version: 0.0.2
Summary: A job queue and task management system with client-server architecture
Author-email: Cornelius Emde <ai@corneliusemde.com>
License:                     GNU AFFERO GENERAL PUBLIC LICENSE
Project-URL: Homepage, https://github.com/cemde/WhatsNext
Project-URL: Issues, https://github.com/cemde/WhatsNext/issues
Project-URL: Documentation, https://whatsnext.readthedocs.io/
Classifier: Development Status :: 3 - Alpha
Classifier: Intended Audience :: Developers
Classifier: License :: OSI Approved :: GNU Affero General Public License v3
Classifier: Programming Language :: Python :: 3
Classifier: Programming Language :: Python :: 3.10
Classifier: Programming Language :: Python :: 3.11
Classifier: Programming Language :: Python :: 3.12
Classifier: Programming Language :: Python :: 3.13
Classifier: Topic :: Software Development :: Libraries :: Python Modules
Requires-Python: >=3.10
License-File: LICENSE
Provides-Extra: cli
Requires-Dist: typer>=0.9.0; extra == "cli"
Requires-Dist: rich>=13.0.0; extra == "cli"
Requires-Dist: pyyaml>=6.0; extra == "cli"
Provides-Extra: server
Requires-Dist: fastapi>=0.100.0; extra == "server"
Requires-Dist: sqlalchemy>=2.0.0; extra == "server"
Requires-Dist: psycopg2-binary>=2.9.0; extra == "server"
Requires-Dist: pydantic-settings>=2.0.0; extra == "server"
Requires-Dist: uvicorn>=0.20.0; extra == "server"
Requires-Dist: alembic>=1.13.0; extra == "server"
Requires-Dist: whatsnext[cli]; extra == "server"
Provides-Extra: client
Requires-Dist: requests>=2.28.0; extra == "client"
Requires-Dist: tabulate>=0.9.0; extra == "client"
Requires-Dist: whatsnext[cli]; extra == "client"
Provides-Extra: all
Requires-Dist: whatsnext[client,server]; extra == "all"
Dynamic: license-file
